autoxeda/__init__.py
autoxeda/core.py
autoxeda-0.1.3.dist-info/LICENSE
autoxeda-0.1.3.dist-info/METADATA
autoxeda-0.1.3.dist-info/WHEEL
autoxeda-0.1.3.dist-info/top_level.txt
autoxeda-0.1.3.dist-info/RECORD
